rim_cin/__init__.py
rim_cin/decision.py
rim_cin/main.py
rim_cin-0.1.0.dist-info/LICENSE
rim_cin-0.1.0.dist-info/METADATA
rim_cin-0.1.0.dist-info/WHEEL
rim_cin-0.1.0.dist-info/RECORD
