Metadata-Version: 2.3
Name: rim_cin
Version: 0.1.0
Summary: Biblioteca Rim
License: MIT
Author: Maiara Cabral, Pedro Henrique
Requires-Python: >=3.10
Classifier: License :: OSI Approved :: MIT License
Classifier: Programming Language :: Python :: 3
Classifier: Programming Language :: Python :: 3.10
Classifier: Programming Language :: Python :: 3.11
Classifier: Programming Language :: Python :: 3.12
Classifier: Programming Language :: Python :: 3.13
Requires-Dist: numpy (==1.26.4)
